CHANGELOG.md
LICENSE
MANIFEST.in
README.md
requirements.txt
requirements_dev.txt
setup.cfg
setup.py
transitland_wrapper/__init__.py
transitland_wrapper/cli.py
transitland_wrapper/transitland.py
transitland_wrapper.egg-info/PKG-INFO
transitland_wrapper.egg-info/SOURCES.txt
transitland_wrapper.egg-info/dependency_links.txt
transitland_wrapper.egg-info/entry_points.txt
transitland_wrapper.egg-info/not-zip-safe
transitland_wrapper.egg-info/requires.txt
transitland_wrapper.egg-info/top_level.txt