Metadata-Version: 2.1
Name: transitland-wrapper
Version: 0.3.0
Summary: Wrapper around transit.land API
Home-page: https://github.com/kylebarron/transitland_wrapper
Author: Kyle Barron
Author-email: kylebarron2@gmail.com
License: MIT license
Keywords: transitland_wrapper
Platform: UNKNOWN
Classifier: Development Status :: 4 - Beta
Classifier: Intended Audience :: Developers
Classifier: License :: OSI Approved :: MIT License
Classifier: Natural Language :: English
Classifier: Programming Language :: Python :: 3
Classifier: Programming Language :: Python :: 3.5
Classifier: Programming Language :: Python :: 3.6
Classifier: Programming Language :: Python :: 3.7
Classifier: Programming Language :: Python :: 3.8
Requires-Python: >=3.5
